sanestack
