Metadata-Version: 1.1
Name: sanestack
Version: 0.0.16
Summary: Check if your dependencies are up to date.
Home-page: https://github.com/mlowicki/sanestack
Author: Michał Łowicki
Author-email: mlowicki@gmail.com
License: MIT
Download-URL: https://github.com/mlowicki/sanestack/tarball/0.0.16
Keywords: dependencies sane stack technical dept updates security fixes upgrades health project requirements
Platform: UNKNOWN
